blprint/__init__.py
blprint/main.py
blprint/modules/__init__.py
blprint/modules/blueprints/__init__.py
blprint/modules/blueprints/commands/__init__.py
blprint/modules/blueprints/commands/create/__init__.py
blprint/modules/blueprints/commands/create/create_command.py
blprint/modules/blueprints/get_blue_print_variables.py
blprint/modules/blueprints/instantiate_blueprint.py
blprint/modules/templates/__init__.py
blprint/modules/templates/format_string.py
blprint/modules/templates/get_template_variables.py
blprint/modules/templates/get_templates_from_blueprint.py
blprint/modules/templates/instantiate_template.py
blprint-0.1.6.dist-info/LICENSE
blprint-0.1.6.dist-info/METADATA
blprint-0.1.6.dist-info/WHEEL
blprint-0.1.6.dist-info/entry_points.txt
blprint-0.1.6.dist-info/RECORD
