Metadata-Version: 2.3
Name: blprint
Version: 0.1.6
Summary: A simple scaffolding cli
Author: Mateus Gurgel
Author-email: mateusgurgel15@gmail.com
Requires-Python: >=3.10,<4.0
Classifier: Programming Language :: Python :: 3
Classifier: Programming Language :: Python :: 3.10
Classifier: Programming Language :: Python :: 3.11
Classifier: Programming Language :: Python :: 3.12
Classifier: Programming Language :: Python :: 3.13
Requires-Dist: jinja2 (>=3.1.5,<4.0.0)
Requires-Dist: typer (>=0.15.1,<0.16.0)
